{
  "05- Delete API" : {
    "transaction" : "05- Delete API",
    "sampleCount" : 14500,
    "errorCount" : 14500,
    "errorPct" : 100.0,
    "meanResTime" : 0.2962068965517228,
    "medianResTime" : 0.0,
    "minResTime" : 0.0,
    "maxResTime" : 7.0,
    "pct1ResTime" : 1.0,
    "pct2ResTime" : 1.0,
    "pct3ResTime" : 1.0,
    "throughput" : 50.024494752603,
    "receivedKBytesPerSec" : 125.98942574898743,
    "sentKBytesPerSec" : 0.0
  },
  "04- Patch API" : {
    "transaction" : "04- Patch API",
    "sampleCount" : 14598,
    "errorCount" : 14598,
    "errorPct" : 100.0,
    "meanResTime" : 0.30305521304288235,
    "medianResTime" : 0.0,
    "minResTime" : 0.0,
    "maxResTime" : 7.0,
    "pct1ResTime" : 1.0,
    "pct2ResTime" : 1.0,
    "pct3ResTime" : 1.0,
    "throughput" : 50.02604452242571,
    "receivedKBytesPerSec" : 125.99332892903897,
    "sentKBytesPerSec" : 0.0
  },
  "Total" : {
    "transaction" : "Total",
    "sampleCount" : 73507,
    "errorCount" : 73507,
    "errorPct" : 100.0,
    "meanResTime" : 0.30862366849415523,
    "medianResTime" : 0.0,
    "minResTime" : 0.0,
    "maxResTime" : 72.0,
    "pct1ResTime" : 1.0,
    "pct2ResTime" : 1.0,
    "pct3ResTime" : 1.0,
    "throughput" : 246.64295540717376,
    "receivedKBytesPerSec" : 621.1837714795911,
    "sentKBytesPerSec" : 0.0
  },
  "03- Put API" : {
    "transaction" : "03- Put API",
    "sampleCount" : 14701,
    "errorCount" : 14701,
    "errorPct" : 100.0,
    "meanResTime" : 0.30208829331337966,
    "medianResTime" : 0.0,
    "minResTime" : 0.0,
    "maxResTime" : 7.0,
    "pct1ResTime" : 1.0,
    "pct2ResTime" : 1.0,
    "pct3ResTime" : 1.0,
    "throughput" : 50.02432990672968,
    "receivedKBytesPerSec" : 125.98901057564048,
    "sentKBytesPerSec" : 0.0
  },
  "02- Post API" : {
    "transaction" : "02- Post API",
    "sampleCount" : 14803,
    "errorCount" : 14803,
    "errorPct" : 100.0,
    "meanResTime" : 0.3052759575761676,
    "medianResTime" : 0.0,
    "minResTime" : 0.0,
    "maxResTime" : 8.0,
    "pct1ResTime" : 1.0,
    "pct2ResTime" : 1.0,
    "pct3ResTime" : 1.0,
    "throughput" : 50.02264079533396,
    "receivedKBytesPerSec" : 125.9847564562171,
    "sentKBytesPerSec" : 0.0
  },
  "01- Get API" : {
    "transaction" : "01- Get API",
    "sampleCount" : 14905,
    "errorCount" : 14905,
    "errorPct" : 100.0,
    "meanResTime" : 0.33592754109359313,
    "medianResTime" : 0.0,
    "minResTime" : 0.0,
    "maxResTime" : 72.0,
    "pct1ResTime" : 1.0,
    "pct2ResTime" : 1.0,
    "pct3ResTime" : 1.0,
    "throughput" : 50.0117437841828,
    "receivedKBytesPerSec" : 125.9573117377026,
    "sentKBytesPerSec" : 0.0
  }
}